<annotation>
	<folder>Result1</folder>
	<filename>Face (355).jpeg</filename>
	<path>C:\Users\moise\OneDrive\Desktop\Main_Traffic__Management\Notes\1_datapreparation\data_images\Face (355).jpeg</path>
	<source>
		<database>Unknown</database>
	</source>
	<size>
		<width>1920</width>
		<height>1088</height>
		<depth>3</depth>
	</size>
	<segmented>0</segmented>
	<object>
		<name>motorcycle</name>
		<pose>Unspecified</pose>
		<truncated>0</truncated>
		<difficult>0</difficult>
		<bndbox>
			<xmin>596</xmin>
			<ymin>678</ymin>
			<xmax>776</xmax>
			<ymax>884</ymax>
		</bndbox>
	</object>
	<object>
		<name>car</name>
		<pose>Unspecified</pose>
		<truncated>0</truncated>
		<difficult>0</difficult>
		<bndbox>
			<xmin>916</xmin>
			<ymin>534</ymin>
			<xmax>1176</xmax>
			<ymax>680</ymax>
		</bndbox>
	</object>
	<object>
		<name>motorcycle</name>
		<pose>Unspecified</pose>
		<truncated>0</truncated>
		<difficult>0</difficult>
		<bndbox>
			<xmin>1430</xmin>
			<ymin>619</ymin>
			<xmax>1527</xmax>
			<ymax>671</ymax>
		</bndbox>
	</object>
	<object>
		<name>motorcycle</name>
		<pose>Unspecified</pose>
		<truncated>0</truncated>
		<difficult>0</difficult>
		<bndbox>
			<xmin>1668</xmin>
			<ymin>607</ymin>
			<xmax>1762</xmax>
			<ymax>677</ymax>
		</bndbox>
	</object>
	<object>
		<name>motorcycle</name>
		<pose>Unspecified</pose>
		<truncated>0</truncated>
		<difficult>0</difficult>
		<bndbox>
			<xmin>769</xmin>
			<ymin>602</ymin>
			<xmax>844</xmax>
			<ymax>669</ymax>
		</bndbox>
	</object>
	<object>
		<name>face</name>
		<pose>Unspecified</pose>
		<truncated>0</truncated>
		<difficult>0</difficult>
		<bndbox>
			<xmin>687</xmin>
			<ymin>588</ymin>
			<xmax>722</xmax>
			<ymax>630</ymax>
		</bndbox>
	</object>
	<object>
		<name>face</name>
		<pose>Unspecified</pose>
		<truncated>0</truncated>
		<difficult>0</difficult>
		<bndbox>
			<xmin>643</xmin>
			<ymin>571</ymin>
			<xmax>667</xmax>
			<ymax>600</ymax>
		</bndbox>
	</object>
	<object>
		<name>tricycle</name>
		<pose>Unspecified</pose>
		<truncated>0</truncated>
		<difficult>0</difficult>
		<bndbox>
			<xmin>495</xmin>
			<ymin>542</ymin>
			<xmax>611</xmax>
			<ymax>646</ymax>
		</bndbox>
	</object>
</annotation>