<annotation>
	<folder>Result1</folder>
	<filename>Face (399).jpeg</filename>
	<path>C:\Users\moise\OneDrive\Desktop\Main_Traffic__Management\Notes\1_datapreparation\data_images\Face (399).jpeg</path>
	<source>
		<database>Unknown</database>
	</source>
	<size>
		<width>1920</width>
		<height>1088</height>
		<depth>3</depth>
	</size>
	<segmented>0</segmented>
	<object>
		<name>face</name>
		<pose>Unspecified</pose>
		<truncated>0</truncated>
		<difficult>0</difficult>
		<bndbox>
			<xmin>1745</xmin>
			<ymin>630</ymin>
			<xmax>1803</xmax>
			<ymax>716</ymax>
		</bndbox>
	</object>
	<object>
		<name>motorcycle</name>
		<pose>Unspecified</pose>
		<truncated>0</truncated>
		<difficult>0</difficult>
		<bndbox>
			<xmin>1180</xmin>
			<ymin>637</ymin>
			<xmax>1271</xmax>
			<ymax>737</ymax>
		</bndbox>
	</object>
	<object>
		<name>motorcycle</name>
		<pose>Unspecified</pose>
		<truncated>0</truncated>
		<difficult>0</difficult>
		<bndbox>
			<xmin>1428</xmin>
			<ymin>643</ymin>
			<xmax>1534</xmax>
			<ymax>727</ymax>
		</bndbox>
	</object>
	<object>
		<name>motorcycle</name>
		<pose>Unspecified</pose>
		<truncated>0</truncated>
		<difficult>0</difficult>
		<bndbox>
			<xmin>1011</xmin>
			<ymin>602</ymin>
			<xmax>1096</xmax>
			<ymax>682</ymax>
		</bndbox>
	</object>
	<object>
		<name>motorcycle</name>
		<pose>Unspecified</pose>
		<truncated>0</truncated>
		<difficult>0</difficult>
		<bndbox>
			<xmin>889</xmin>
			<ymin>582</ymin>
			<xmax>953</xmax>
			<ymax>661</ymax>
		</bndbox>
	</object>
	<object>
		<name>motorcycle</name>
		<pose>Unspecified</pose>
		<truncated>0</truncated>
		<difficult>0</difficult>
		<bndbox>
			<xmin>134</xmin>
			<ymin>514</ymin>
			<xmax>177</xmax>
			<ymax>587</ymax>
		</bndbox>
	</object>
	<object>
		<name>face</name>
		<pose>Unspecified</pose>
		<truncated>0</truncated>
		<difficult>0</difficult>
		<bndbox>
			<xmin>1213</xmin>
			<ymin>552</ymin>
			<xmax>1239</xmax>
			<ymax>580</ymax>
		</bndbox>
	</object>
	<object>
		<name>face</name>
		<pose>Unspecified</pose>
		<truncated>0</truncated>
		<difficult>0</difficult>
		<bndbox>
			<xmin>1464</xmin>
			<ymin>568</ymin>
			<xmax>1490</xmax>
			<ymax>596</ymax>
		</bndbox>
	</object>
</annotation>