<annotation>
	<folder>Result1</folder>
	<filename>Sasakyan00541.jpeg</filename>
	<path>C:\Users\moise\OneDrive\Desktop\Main_Traffic__Management\Notes\1_datapreparation\data_images\Sasakyan00541.jpeg</path>
	<source>
		<database>Unknown</database>
	</source>
	<size>
		<width>1920</width>
		<height>1088</height>
		<depth>3</depth>
	</size>
	<segmented>0</segmented>
	<object>
		<name>face</name>
		<pose>Unspecified</pose>
		<truncated>0</truncated>
		<difficult>0</difficult>
		<bndbox>
			<xmin>1157</xmin>
			<ymin>733</ymin>
			<xmax>1246</xmax>
			<ymax>884</ymax>
		</bndbox>
	</object>
	<object>
		<name>face</name>
		<pose>Unspecified</pose>
		<truncated>0</truncated>
		<difficult>0</difficult>
		<bndbox>
			<xmin>1263</xmin>
			<ymin>586</ymin>
			<xmax>1318</xmax>
			<ymax>709</ymax>
		</bndbox>
	</object>
	<object>
		<name>face</name>
		<pose>Unspecified</pose>
		<truncated>0</truncated>
		<difficult>0</difficult>
		<bndbox>
			<xmin>1767</xmin>
			<ymin>584</ymin>
			<xmax>1800</xmax>
			<ymax>624</ymax>
		</bndbox>
	</object>
	<object>
		<name>face</name>
		<pose>Unspecified</pose>
		<truncated>0</truncated>
		<difficult>0</difficult>
		<bndbox>
			<xmin>1712</xmin>
			<ymin>583</ymin>
			<xmax>1761</xmax>
			<ymax>625</ymax>
		</bndbox>
	</object>
	<object>
		<name>face</name>
		<pose>Unspecified</pose>
		<truncated>0</truncated>
		<difficult>0</difficult>
		<bndbox>
			<xmin>1171</xmin>
			<ymin>609</ymin>
			<xmax>1204</xmax>
			<ymax>647</ymax>
		</bndbox>
	</object>
	<object>
		<name>face</name>
		<pose>Unspecified</pose>
		<truncated>0</truncated>
		<difficult>0</difficult>
		<bndbox>
			<xmin>512</xmin>
			<ymin>698</ymin>
			<xmax>723</xmax>
			<ymax>1047</ymax>
		</bndbox>
	</object>
	<object>
		<name>face</name>
		<pose>Unspecified</pose>
		<truncated>0</truncated>
		<difficult>0</difficult>
		<bndbox>
			<xmin>728</xmin>
			<ymin>471</ymin>
			<xmax>773</xmax>
			<ymax>520</ymax>
		</bndbox>
	</object>
	<object>
		<name>face</name>
		<pose>Unspecified</pose>
		<truncated>0</truncated>
		<difficult>0</difficult>
		<bndbox>
			<xmin>644</xmin>
			<ymin>446</ymin>
			<xmax>678</xmax>
			<ymax>486</ymax>
		</bndbox>
	</object>
	<object>
		<name>face</name>
		<pose>Unspecified</pose>
		<truncated>0</truncated>
		<difficult>0</difficult>
		<bndbox>
			<xmin>600</xmin>
			<ymin>433</ymin>
			<xmax>625</xmax>
			<ymax>469</ymax>
		</bndbox>
	</object>
	<object>
		<name>face</name>
		<pose>Unspecified</pose>
		<truncated>0</truncated>
		<difficult>0</difficult>
		<bndbox>
			<xmin>417</xmin>
			<ymin>400</ymin>
			<xmax>435</xmax>
			<ymax>428</ymax>
		</bndbox>
	</object>
	<object>
		<name>face</name>
		<pose>Unspecified</pose>
		<truncated>0</truncated>
		<difficult>0</difficult>
		<bndbox>
			<xmin>468</xmin>
			<ymin>460</ymin>
			<xmax>504</xmax>
			<ymax>500</ymax>
		</bndbox>
	</object>
	<object>
		<name>face</name>
		<pose>Unspecified</pose>
		<truncated>0</truncated>
		<difficult>0</difficult>
		<bndbox>
			<xmin>550</xmin>
			<ymin>460</ymin>
			<xmax>585</xmax>
			<ymax>496</ymax>
		</bndbox>
	</object>
	<object>
		<name>face</name>
		<pose>Unspecified</pose>
		<truncated>0</truncated>
		<difficult>0</difficult>
		<bndbox>
			<xmin>1049</xmin>
			<ymin>659</ymin>
			<xmax>1145</xmax>
			<ymax>792</ymax>
		</bndbox>
	</object>
</annotation>