<annotation>
	<folder>Result1</folder>
	<filename>Vehicle (156).jpeg</filename>
	<path>C:\Users\moise\OneDrive\Desktop\video_vehicles\Result1\Vehicle (156).jpeg</path>
	<source>
		<database>Unknown</database>
	</source>
	<size>
		<width>1920</width>
		<height>1088</height>
		<depth>3</depth>
	</size>
	<segmented>0</segmented>
	<object>
		<name>motorcycle</name>
		<pose>Unspecified</pose>
		<truncated>0</truncated>
		<difficult>0</difficult>
		<bndbox>
			<xmin>475</xmin>
			<ymin>274</ymin>
			<xmax>621</xmax>
			<ymax>391</ymax>
		</bndbox>
	</object>
	<object>
		<name>motorcycle</name>
		<pose>Unspecified</pose>
		<truncated>0</truncated>
		<difficult>0</difficult>
		<bndbox>
			<xmin>669</xmin>
			<ymin>507</ymin>
			<xmax>819</xmax>
			<ymax>725</ymax>
		</bndbox>
	</object>
	<object>
		<name>motorcycle</name>
		<pose>Unspecified</pose>
		<truncated>0</truncated>
		<difficult>0</difficult>
		<bndbox>
			<xmin>1052</xmin>
			<ymin>425</ymin>
			<xmax>1166</xmax>
			<ymax>589</ymax>
		</bndbox>
	</object>
	<object>
		<name>motorcycle</name>
		<pose>Unspecified</pose>
		<truncated>0</truncated>
		<difficult>0</difficult>
		<bndbox>
			<xmin>1130</xmin>
			<ymin>379</ymin>
			<xmax>1241</xmax>
			<ymax>493</ymax>
		</bndbox>
	</object>
	<object>
		<name>motorcycle</name>
		<pose>Unspecified</pose>
		<truncated>0</truncated>
		<difficult>0</difficult>
		<bndbox>
			<xmin>582</xmin>
			<ymin>187</ymin>
			<xmax>628</xmax>
			<ymax>279</ymax>
		</bndbox>
	</object>
	<object>
		<name>truck</name>
		<pose>Unspecified</pose>
		<truncated>1</truncated>
		<difficult>0</difficult>
		<bndbox>
			<xmin>693</xmin>
			<ymin>1</ymin>
			<xmax>998</xmax>
			<ymax>177</ymax>
		</bndbox>
	</object>
	<object>
		<name>car</name>
		<pose>Unspecified</pose>
		<truncated>0</truncated>
		<difficult>0</difficult>
		<bndbox>
			<xmin>1377</xmin>
			<ymin>143</ymin>
			<xmax>1636</xmax>
			<ymax>255</ymax>
		</bndbox>
	</object>
	<object>
		<name>car</name>
		<pose>Unspecified</pose>
		<truncated>0</truncated>
		<difficult>0</difficult>
		<bndbox>
			<xmin>1446</xmin>
			<ymin>305</ymin>
			<xmax>1845</xmax>
			<ymax>469</ymax>
		</bndbox>
	</object>
	<object>
		<name>bus</name>
		<pose>Unspecified</pose>
		<truncated>1</truncated>
		<difficult>0</difficult>
		<bndbox>
			<xmin>502</xmin>
			<ymin>1</ymin>
			<xmax>644</xmax>
			<ymax>148</ymax>
		</bndbox>
	</object>
</annotation>
