<annotation>
	<folder>Result1</folder>
	<filename>Vehicle (51).jpeg</filename>
	<path>C:\Users\moise\OneDrive\Desktop\video_vehicles\Result1\Vehicle (51).jpeg</path>
	<source>
		<database>Unknown</database>
	</source>
	<size>
		<width>1920</width>
		<height>1088</height>
		<depth>3</depth>
	</size>
	<segmented>0</segmented>
	<object>
		<name>car</name>
		<pose>Unspecified</pose>
		<truncated>0</truncated>
		<difficult>0</difficult>
		<bndbox>
			<xmin>295</xmin>
			<ymin>504</ymin>
			<xmax>605</xmax>
			<ymax>736</ymax>
		</bndbox>
	</object>
	<object>
		<name>car</name>
		<pose>Unspecified</pose>
		<truncated>0</truncated>
		<difficult>0</difficult>
		<bndbox>
			<xmin>534</xmin>
			<ymin>348</ymin>
			<xmax>817</xmax>
			<ymax>521</ymax>
		</bndbox>
	</object>
	<object>
		<name>car</name>
		<pose>Unspecified</pose>
		<truncated>0</truncated>
		<difficult>0</difficult>
		<bndbox>
			<xmin>784</xmin>
			<ymin>588</ymin>
			<xmax>1175</xmax>
			<ymax>828</ymax>
		</bndbox>
	</object>
	<object>
		<name>truck</name>
		<pose>Unspecified</pose>
		<truncated>0</truncated>
		<difficult>0</difficult>
		<bndbox>
			<xmin>1161</xmin>
			<ymin>237</ymin>
			<xmax>1346</xmax>
			<ymax>377</ymax>
		</bndbox>
	</object>
	<object>
		<name>car</name>
		<pose>Unspecified</pose>
		<truncated>0</truncated>
		<difficult>0</difficult>
		<bndbox>
			<xmin>999</xmin>
			<ymin>252</ymin>
			<xmax>1180</xmax>
			<ymax>366</ymax>
		</bndbox>
	</object>
	<object>
		<name>car</name>
		<pose>Unspecified</pose>
		<truncated>0</truncated>
		<difficult>0</difficult>
		<bndbox>
			<xmin>904</xmin>
			<ymin>255</ymin>
			<xmax>1064</xmax>
			<ymax>350</ymax>
		</bndbox>
	</object>
	<object>
		<name>car</name>
		<pose>Unspecified</pose>
		<truncated>0</truncated>
		<difficult>0</difficult>
		<bndbox>
			<xmin>758</xmin>
			<ymin>232</ymin>
			<xmax>969</xmax>
			<ymax>329</ymax>
		</bndbox>
	</object>
	<object>
		<name>car</name>
		<pose>Unspecified</pose>
		<truncated>0</truncated>
		<difficult>0</difficult>
		<bndbox>
			<xmin>1346</xmin>
			<ymin>229</ymin>
			<xmax>1458</xmax>
			<ymax>332</ymax>
		</bndbox>
	</object>
	<object>
		<name>motorcycle</name>
		<pose>Unspecified</pose>
		<truncated>0</truncated>
		<difficult>0</difficult>
		<bndbox>
			<xmin>754</xmin>
			<ymin>473</ymin>
			<xmax>894</xmax>
			<ymax>596</ymax>
		</bndbox>
	</object>
	<object>
		<name>motorcycle</name>
		<pose>Unspecified</pose>
		<truncated>0</truncated>
		<difficult>0</difficult>
		<bndbox>
			<xmin>1269</xmin>
			<ymin>618</ymin>
			<xmax>1430</xmax>
			<ymax>780</ymax>
		</bndbox>
	</object>
	<object>
		<name>motorcycle</name>
		<pose>Unspecified</pose>
		<truncated>0</truncated>
		<difficult>0</difficult>
		<bndbox>
			<xmin>322</xmin>
			<ymin>304</ymin>
			<xmax>395</xmax>
			<ymax>404</ymax>
		</bndbox>
	</object>
	<object>
		<name>motorcycle</name>
		<pose>Unspecified</pose>
		<truncated>0</truncated>
		<difficult>0</difficult>
		<bndbox>
			<xmin>377</xmin>
			<ymin>371</ymin>
			<xmax>459</xmax>
			<ymax>488</ymax>
		</bndbox>
	</object>
	<object>
		<name>motorcycle</name>
		<pose>Unspecified</pose>
		<truncated>0</truncated>
		<difficult>0</difficult>
		<bndbox>
			<xmin>182</xmin>
			<ymin>314</ymin>
			<xmax>255</xmax>
			<ymax>429</ymax>
		</bndbox>
	</object>
	<object>
		<name>motorcycle</name>
		<pose>Unspecified</pose>
		<truncated>0</truncated>
		<difficult>0</difficult>
		<bndbox>
			<xmin>576</xmin>
			<ymin>261</ymin>
			<xmax>652</xmax>
			<ymax>355</ymax>
		</bndbox>
	</object>
	<object>
		<name>motorcycle</name>
		<pose>Unspecified</pose>
		<truncated>0</truncated>
		<difficult>0</difficult>
		<bndbox>
			<xmin>508</xmin>
			<ymin>293</ymin>
			<xmax>586</xmax>
			<ymax>380</ymax>
		</bndbox>
	</object>
	<object>
		<name>motorcycle</name>
		<pose>Unspecified</pose>
		<truncated>0</truncated>
		<difficult>0</difficult>
		<bndbox>
			<xmin>740</xmin>
			<ymin>637</ymin>
			<xmax>880</xmax>
			<ymax>834</ymax>
		</bndbox>
	</object>
	<object>
		<name>motorcycle</name>
		<pose>Unspecified</pose>
		<truncated>0</truncated>
		<difficult>0</difficult>
		<bndbox>
			<xmin>946</xmin>
			<ymin>423</ymin>
			<xmax>1078</xmax>
			<ymax>541</ymax>
		</bndbox>
	</object>
	<object>
		<name>motorcycle</name>
		<pose>Unspecified</pose>
		<truncated>0</truncated>
		<difficult>0</difficult>
		<bndbox>
			<xmin>961</xmin>
			<ymin>516</ymin>
			<xmax>1080</xmax>
			<ymax>646</ymax>
		</bndbox>
	</object>
</annotation>
